README.md
setup.py
NewThread/Thread.py
NewThread/__init__.py
NewThread.egg-info/PKG-INFO
NewThread.egg-info/SOURCES.txt
NewThread.egg-info/dependency_links.txt
NewThread.egg-info/top_level.txt