Metadata-Version: 2.1
Name: NewThread
Version: 1.0.2
Summary: threading.Thread类的继承和拓展
Home-page: UNKNOWN
Author: 孙亮
Author-email: 3028772928@qq.com
License: UNKNOWN
Platform: UNKNOWN
Requires-Python: >=3.6
